symbiotic/__init__.py
symbiotic/actions.py
symbiotic/app.py
symbiotic/colours.py
symbiotic/containers.py
symbiotic/devices.py
symbiotic/event_bus.py
symbiotic/exceptions.py
symbiotic/parameters.py
symbiotic/schedule.py
symbiotic/sensors.py
symbiotic/services.py
symbiotic/validators.py
symbiotic/web/__init__.py
symbiotic/web/http.py
tests/__init__.py
tests/conftest.py
tests/test_actions.py
tests/test_app.py
tests/test_devices.py
tests/test_event_bus.py
tests/test_schedule.py
tests/test_services.py
symbiotic-1.0.0a3.dist-info/LICENSE
symbiotic-1.0.0a3.dist-info/METADATA
symbiotic-1.0.0a3.dist-info/WHEEL
symbiotic-1.0.0a3.dist-info/top_level.txt
symbiotic-1.0.0a3.dist-info/RECORD
