Metadata-Version: 2.1
Name: symbiotic
Version: 1.0.0a3
Summary: Connect your smart devices and sensors to create complex, schedulable actions.
Home-page: https://github.com/StefanoFrazzetto/symbiotic
Author: Stefano Frazzetto
Author-email: stefano+symbiotic@hey.com
License: Apache-2.0
Project-URL: Bug Reports, https://github.com/StefanoFrazzetto/symbiotic/issues
Project-URL: Source, https://github.com/StefanoFrazzetto/symbiotic
Keywords: automation,dependency-injection,event-bus,iot,schedule,security,smart-devices
Platform: UNKNOWN
Classifier: Development Status :: 3 - Alpha
Classifier: Programming Language :: Python :: 3
Classifier: Programming Language :: Python :: 3.6
Classifier: Programming Language :: Python :: 3.7
Classifier: Programming Language :: Python :: 3.8
Classifier: Programming Language :: Python :: 3.9
Classifier: License :: OSI Approved :: Apache Software License
Classifier: Operating System :: OS Independent
Classifier: Topic :: Home Automation
Classifier: Topic :: Software Development :: Libraries
Classifier: Topic :: System :: Hardware
Requires-Python: >=3.6
Requires-Dist: dependency-injector (>=4.11)
Requires-Dist: event-bus
Requires-Dist: gpiozero
Requires-Dist: pigpio
Requires-Dist: pydantic
Requires-Dist: schema
Requires-Dist: requests
Provides-Extra: dev
Requires-Dist: autopep8 ; extra == 'dev'
Requires-Dist: flake8 ; extra == 'dev'
Provides-Extra: test
Requires-Dist: pytest ; extra == 'test'
Requires-Dist: pytest-mock ; extra == 'test'
Requires-Dist: freezegun ; extra == 'test'
Provides-Extra: yaml
Requires-Dist: PyYAML (>=5.4) ; extra == 'yaml'
